<metadata xml:lang="en"><Esri><CreaDate>20160620</CreaDate><CreaTime>12183700</CreaTime><ArcGISFormat>1.0</ArcGISFormat><SyncOnce>TRUE</SyncOnce><ModDate>20160623</ModDate><ModTime>9380600</ModTime><scaleRange><minScale>150000000</minScale><maxScale>5000</maxScale></scaleRange><ArcGISProfile>ItemDescription</ArcGISProfile></Esri><tool name="StreamNetworktoRAPID" displayname="Stream Network to RAPID" toolboxalias="RAPIDTools" xmlns=""><arcToolboxHelpPath>c:\program files (x86)\arcgis\desktop10.3\Help\gp</arcToolboxHelpPath><parameters><param name="RAPID Output Folder" displayname="rapid_out_folder" type="Required" direction="Input" datatype="Folder" expression="RAPID Output Folder"><dialogReference>&lt;DIV STYLE="text-align:Left;"&gt;&lt;DIV&gt;&lt;P&gt;&lt;SPAN&gt;The folder which all the new RAPID files will be sent to.&lt;/SPAN&gt;&lt;/P&gt;&lt;/DIV&gt;&lt;/DIV&gt;</dialogReference></param><param name="Drainage_Lines" displayname="Input Drainage Lines" type="Required" direction="Input" datatype="Feature Layer" expression="Drainage_Lines"><dialogReference>&lt;DIV STYLE="text-align:Left;"&gt;&lt;DIV&gt;&lt;P&gt;&lt;SPAN&gt;The drainage lines for the desired area.&lt;/SPAN&gt;&lt;/P&gt;&lt;/DIV&gt;&lt;/DIV&gt;</dialogReference></param><param name="Input_Catchment_Features" displayname="Input Catchment Features" type="Required" direction="Input" datatype="Feature Layer" expression="Input_Catchment_Features"><dialogReference>&lt;DIV STYLE="text-align:Left;"&gt;&lt;DIV&gt;&lt;P&gt;&lt;SPAN&gt;The catchments which accompany the drainage lines.&lt;/SPAN&gt;&lt;/P&gt;&lt;/DIV&gt;&lt;/DIV&gt;</dialogReference></param><param name="Stream_ID_Catchments" displayname="Catchments Stream ID" type="Required" direction="Input" datatype="Field" expression="Stream_ID_Catchments"><dialogReference>&lt;DIV STYLE="text-align:Left;"&gt;&lt;DIV&gt;&lt;P&gt;&lt;SPAN&gt;The stream ID for the catchments.&lt;/SPAN&gt;&lt;/P&gt;&lt;/DIV&gt;&lt;/DIV&gt;</dialogReference></param></parameters><summary>&lt;DIV STYLE="text-align:Left;"&gt;&lt;DIV&gt;&lt;DIV&gt;&lt;P&gt;&lt;SPAN&gt;This converts a stream network to the necessary files for RAPID.&lt;/SPAN&gt;&lt;/P&gt;&lt;/DIV&gt;&lt;/DIV&gt;&lt;/DIV&gt;</summary><usage>&lt;DIV STYLE="text-align:Left;"&gt;&lt;DIV&gt;&lt;P&gt;&lt;SPAN&gt;This was designed to be run with HydroSHEDS to Stream Network. The files generated from HydroSHEDS to Stream Network will serve as inputs to this script.&lt;/SPAN&gt;&lt;/P&gt;&lt;/DIV&gt;&lt;/DIV&gt;</usage></tool><dataIdInfo><idCitation><resTitle>Stream Network to RAPID</resTitle></idCitation><idAbs>&lt;DIV STYLE="text-align:Left;"&gt;&lt;DIV&gt;&lt;DIV&gt;&lt;P&gt;&lt;SPAN&gt;This converts a stream network to the necessary files for RAPID.&lt;/SPAN&gt;&lt;/P&gt;&lt;/DIV&gt;&lt;/DIV&gt;&lt;/DIV&gt;</idAbs></dataIdInfo><distInfo><distributor><distorFormat><formatName>ArcToolbox Tool</formatName></distorFormat></distributor></distInfo><mdHrLv><ScopeCd value="005"/></mdHrLv></metadata>
